matlab_connection/__init__.py
matlab_connection/matlab_connection.py
matlab_connection/mfiles/README.txt
matlab_connection/mfiles/function_from_python.m
matlab_connection/mfiles/script_from_python.m
matlab_connection-0.0.4.dist-info/METADATA
matlab_connection-0.0.4.dist-info/WHEEL
matlab_connection-0.0.4.dist-info/top_level.txt
matlab_connection-0.0.4.dist-info/RECORD
