Metadata-Version: 2.1
Name: matlab-connection
Version: 0.0.4
Summary: Package to streamline reading from and writing data to MATLAB from python
Home-page: https://github.com/pckosek/matlab_connection
Author: Paul Kosek
Author-email: pckosek@fcps.edu
License: UNKNOWN
Keywords: MATLAB,python
Platform: UNKNOWN
Classifier: Programming Language :: Python :: 3
Classifier: License :: OSI Approved :: MIT License
Classifier: Operating System :: OS Independent
